LICENSE.txt
README.md
setup.py
rocket_lab_package/__init__.py
rocket_lab_package/rocket_lab_package.py
rocket_lab_package.egg-info/PKG-INFO
rocket_lab_package.egg-info/SOURCES.txt
rocket_lab_package.egg-info/dependency_links.txt
rocket_lab_package.egg-info/requires.txt
rocket_lab_package.egg-info/top_level.txt