Metadata-Version: 2.1
Name: rocket_lab_package
Version: 1.0.0
Summary: LAB package for academic learning purposes.
Home-page: http://pypi.python.org/pypi/rocket/
Author: Guerinik Abderrahmane
Author-email: ca.guerinik@esi-sba.dz
License: LICENSE.txt
License-File: LICENSE.txt
Requires-Dist: rocket_lab_package
